sphinxfeed.py
sphinxfeed_lsaffre-0.3.5.dist-info/METADATA
sphinxfeed_lsaffre-0.3.5.dist-info/WHEEL
sphinxfeed_lsaffre-0.3.5.dist-info/licenses/LICENSE
sphinxfeed_lsaffre-0.3.5.dist-info/RECORD
