Metadata-Version: 2.3
Name: sphinxfeed-lsaffre
Version: 0.3.5
Summary: Sphinx extension for generating RSS feeds
Project-URL: homepage, https://github.com/lsaffre/sphinxfeed
Project-URL: issues, https://github.com/lsaffre/sphinxfeed/issues
Author-email: Fergus Doyle <fergus.doyle@largeblue.com>, Luc Saffre <luc@saffre-rumma.net>, Jordan Cook <jordan.cook.git@proton.me>
Maintainer-email: Luc Saffre <luc@saffre-rumma.net>
License: Copyright 2011 Fergus Doyle <fergus.doyle@largeblue.com>
License-File: LICENSE
Classifier: Development Status :: 4 - Beta
Classifier: Environment :: Console
Classifier: Environment :: Web Environment
Classifier: Intended Audience :: Developers
Classifier: License :: OSI Approved :: BSD License
Classifier: Operating System :: OS Independent
Classifier: Programming Language :: Python
Classifier: Programming Language :: Python :: 3
Classifier: Programming Language :: Python :: 3.8
Classifier: Programming Language :: Python :: 3.9
Classifier: Programming Language :: Python :: 3.10
Classifier: Programming Language :: Python :: 3.11
Classifier: Programming Language :: Python :: 3.12
Classifier: Topic :: Documentation
Classifier: Topic :: Utilities
Requires-Python: >=3.8
Requires-Dist: feedgen
Requires-Dist: python-dateutil
Requires-Dist: sphinx
Provides-Extra: dev
Requires-Dist: hatch; extra == 'dev'
Requires-Dist: pytest; extra == 'dev'
Requires-Dist: pytest-cov; extra == 'dev'
